picblocks
utils
