Metadata-Version: 2.1
Name: picblocks
Version: 1.1.4
Summary: A library for code similarity estimation using PIC hashing over basic blocks.
Home-page: https://github.com/danielplohmann/picblocks
Author: Daniel Plohmann
Author-email: daniel.plohmann@mailbox.org
License: BSD 2-Clause
Platform: UNKNOWN
Classifier: Development Status :: 4 - Beta
Classifier: License :: OSI Approved :: BSD License
Classifier: Operating System :: OS Independent
Classifier: Programming Language :: Python :: 2.7
Classifier: Programming Language :: Python :: 3
Classifier: Topic :: Security
Classifier: Topic :: Software Development :: Disassemblers
Requires-Python: >=3.6
